channels_lite/__init__.py
channels_lite/layers/__init__.py
channels_lite/layers/aio.py
channels_lite/layers/core.py
channels_lite/management/__init__.py
channels_lite/management/commands/__init__.py
channels_lite/management/commands/clean_channels.py
channels_lite/migrations/0001_initial.py
channels_lite/migrations/__init__.py
channels_lite/models.py
channels_lite/py.typed
channels_lite/router.py
channels_lite/serializers.py
channels_lite-0.4.0.dist-info/WHEEL
channels_lite-0.4.0.dist-info/METADATA
channels_lite-0.4.0.dist-info/RECORD
