Metadata-Version: 2.3
Name: channels-lite
Version: 0.4.0
Summary: Lightweight Django Channels layer backed by SQLite database
Keywords: django,channels,websockets,asgi,sqlite,channel-layer
Author: Tobi
Author-email: Tobi <tobidegnon@proton.me>
License: MIT
Classifier: Development Status :: 3 - Alpha
Classifier: Environment :: Web Environment
Classifier: Framework :: Django
Classifier: Framework :: Django :: 5.2
Classifier: Framework :: Django :: 6.0
Classifier: Intended Audience :: Developers
Classifier: License :: OSI Approved :: MIT License
Classifier: Operating System :: OS Independent
Classifier: Programming Language :: Python
Classifier: Programming Language :: Python :: 3
Classifier: Programming Language :: Python :: 3.10
Classifier: Programming Language :: Python :: 3.11
Classifier: Programming Language :: Python :: 3.12
Classifier: Programming Language :: Python :: 3.13
Classifier: Programming Language :: Python :: 3.14
Classifier: Programming Language :: Python :: 3 :: Only
Classifier: Topic :: Internet :: WWW/HTTP
Classifier: Topic :: Software Development :: Libraries :: Python Modules
Requires-Dist: channels[daphne,types]>=4.3.2
Requires-Dist: aiosqlite>=0.22.1 ; extra == 'aio'
Requires-Dist: aiosqlitepool>=1.0.0 ; extra == 'aio'
Requires-Dist: msgspec>=0.19.0 ; extra == 'aio'
Requires-Dist: cryptography>=46.0.3 ; extra == 'cryptography'
Requires-Python: >=3.10
Project-URL: Changelog, https://github.com/Tobi-De/channels-lite/releases
Project-URL: Homepage, https://github.com/Tobi-De/channels-lite
Project-URL: Issues, https://github.com/Tobi-De/channels-lite/issues
Project-URL: Repository, https://github.com/Tobi-De/channels-lite
Provides-Extra: aio
Provides-Extra: cryptography
